mongoaudit/__init__.py
mongoaudit/__main__.py
mongoaudit/cards.py
mongoaudit/palette.py
mongoaudit/picmagic.py
mongoaudit/test_mongo.py
mongoaudit/tools.py
mongoaudit/version.py
mongoaudit/widgets.py
mongoaudit/data/__init__.py
mongoaudit/data/bars_max.bmp
mongoaudit/data/bars_min.bmp
mongoaudit/data/check_advanced.bmp
mongoaudit/data/check_basic.bmp
mongoaudit/data/tests.json
mongoaudit/data/welcome.bmp
mongoaudit/testers/__init__.py
mongoaudit/testers/cve.py
mongoaudit/testers/decorators.py
mongoaudit/testers/roles.py
mongoaudit/testers/testers.py
mongoaudit/testers/tls.py
mongoaudit/testers/utils.py
mongoaudit-0.1.1.dist-info/LICENSE
mongoaudit-0.1.1.dist-info/METADATA
mongoaudit-0.1.1.dist-info/WHEEL
mongoaudit-0.1.1.dist-info/entry_points.txt
mongoaudit-0.1.1.dist-info/top_level.txt
mongoaudit-0.1.1.dist-info/RECORD
