Metadata-Version: 1.1
Name: mongoaudit
Version: 0.1.1
Summary: An automated pentesting tool that lets you know if your MongoDB instances are properly secured
Home-page: https://github.com/stampery/mongoaudit
Author: Stampery Inc.
Author-email: info@stampery.com
License: MIT
Platform: UNKNOWN
Classifier: Development Status :: 4 - Beta
Classifier: Environment :: Console
Classifier: Intended Audience :: System Administrators
Classifier: Intended Audience :: Developers
Classifier: License :: OSI Approved :: MIT License
Classifier: Natural Language :: English
Classifier: Programming Language :: Python :: 2.7
Classifier: Programming Language :: Python :: 3.6
Classifier: Topic :: Database
Classifier: Topic :: Database :: Front-Ends
Classifier: Topic :: Security
Classifier: Topic :: System :: Systems Administration
